etacorpy/__init__.py
etacorpy/calc_eta_n.py
etacorpy/calc_rta_n.py
etacorpy/independence_test.py
etacorpy-0.1.5.dist-info/LICENSE
etacorpy-0.1.5.dist-info/METADATA
etacorpy-0.1.5.dist-info/WHEEL
etacorpy-0.1.5.dist-info/top_level.txt
etacorpy-0.1.5.dist-info/RECORD
